tabpfn_common_utils/__init__.py
tabpfn_common_utils/_version.py
tabpfn_common_utils/expense_estimation.py
tabpfn_common_utils/regression_pred_result.py
tabpfn_common_utils/utils.py
tabpfn_common_utils/telemetry/__init__.py
tabpfn_common_utils/telemetry/core/__init__.py
tabpfn_common_utils/telemetry/core/config.py
tabpfn_common_utils/telemetry/core/decorators.py
tabpfn_common_utils/telemetry/core/events.py
tabpfn_common_utils/telemetry/core/runtime.py
tabpfn_common_utils/telemetry/core/service.py
tabpfn_common_utils/telemetry/core/state.py
tabpfn_common_utils/telemetry/interactive/__init__.py
tabpfn_common_utils/telemetry/interactive/flows.py
tabpfn_common_utils/telemetry/interactive/prompts/base.py
tabpfn_common_utils/telemetry/interactive/prompts/identity.py
tabpfn_common_utils/telemetry/interactive/prompts/newsletter.py
tabpfn_common_utils/py.typed
tabpfn_common_utils-0.2.13.dist-info/METADATA
tabpfn_common_utils-0.2.13.dist-info/WHEEL
tabpfn_common_utils-0.2.13.dist-info/licenses/LICENSE
tabpfn_common_utils-0.2.13.dist-info/RECORD
