Metadata-Version: 2.4
Name: tabpfn-common-utils
Version: 0.2.13
Summary: Utilities shared between TabPFN codebases
Project-URL: Homepage, https://github.com/priorlabs/tabpfn_common_utils
Project-URL: Issues, https://github.com/priorlabs/tabpfn_common_utils/issues
Author-email: Prior Labs <hello@priorlabs.ai>
Maintainer-email: Prior Labs <hello@priorlabs.ai>
License-File: LICENSE
Keywords: machine-learning,tabpfn,utilities
Classifier: Programming Language :: Python :: 3
Classifier: Programming Language :: Python :: 3.9
Classifier: Programming Language :: Python :: 3.10
Classifier: Programming Language :: Python :: 3.11
Classifier: Programming Language :: Python :: 3.12
Classifier: Programming Language :: Python :: 3.13
Requires-Python: >=3.9
Requires-Dist: filelock>=3.19.1
Requires-Dist: numpy>=1.21.6
Requires-Dist: pandas<3,>=1.4.0
Requires-Dist: platformdirs>=4
Requires-Dist: posthog~=6.7
Requires-Dist: requests>=2.32.5
Requires-Dist: ruff>=0.11.6
Requires-Dist: scikit-learn>=1.2.0
Requires-Dist: typing-extensions<5,>=4.12
Provides-Extra: build
Requires-Dist: build>=1.0.0; extra == 'build'
Requires-Dist: hatchling>=1.25; extra == 'build'
Requires-Dist: twine>=5.0.0; extra == 'build'
Provides-Extra: dev
Requires-Dist: pyright>=1.1.399; extra == 'dev'
Requires-Dist: pytest-cov>=5; extra == 'dev'
Requires-Dist: pytest>=8.3; extra == 'dev'
Requires-Dist: ruff>=0.9; extra == 'dev'
Provides-Extra: telemetry-interactive
